MT5TrdHelper/__init__.py
MT5TrdHelper/connect/__init__.py
MT5TrdHelper/connect/connection.py
MT5TrdHelper/exchange/__init__.py
MT5TrdHelper/exchange/exchange_base.py
MT5TrdHelper/exchange/mt5_exchange.py
MT5TrdHelper/exchange/symbol_base.py
MT5TrdHelper/helpers/__init__.py
MT5TrdHelper/helpers/entries.py
MT5TrdHelper/helpers/help_functions.py
MT5TrdHelper/trade_execution/__init__.py
MT5TrdHelper/trade_execution/trade.py
MT5TrdHelper-0.1.4.dist-info/LICENSE
MT5TrdHelper-0.1.4.dist-info/METADATA
MT5TrdHelper-0.1.4.dist-info/WHEEL
MT5TrdHelper-0.1.4.dist-info/top_level.txt
MT5TrdHelper-0.1.4.dist-info/RECORD
