Metadata-Version: 2.1
Name: MT5TrdHelper
Version: 0.1.4
Summary: Python MT5 trade helpers
Author: Nazrul Islam
Author-email: nazrulgithub@gmail.com
License: UNKNOWN
Keywords: python,mt5 python,mt5 python algotrading,forex algotrading,forex python
Platform: UNKNOWN
Classifier: Development Status :: 3 - Alpha
Classifier: Intended Audience :: Education
Classifier: Programming Language :: Python :: 3
Classifier: Operating System :: Microsoft :: Windows
License-File: LICENSE
Requires-Dist: pandas
Requires-Dist: python-dateutil
Requires-Dist: pymt5adapter
Requires-Dist: localconfig
